python_local/__init__.py
python_local/server.py
iflow_mcp_python_local-0.1.1.dist-info/METADATA
iflow_mcp_python_local-0.1.1.dist-info/WHEEL
iflow_mcp_python_local-0.1.1.dist-info/entry_points.txt
iflow_mcp_python_local-0.1.1.dist-info/RECORD
