Metadata-Version: 2.4
Name: iflow-mcp_python-local
Version: 0.1.1
Summary: An MCP Server to run python locally
Author-email: Alex Velikanov <alex25368@gmail.com>
Requires-Python: >=3.12
Requires-Dist: mcp>=1.1.0
